{"format":1,"version":"4.5.3","settings":"b3a0bff7154d5bbec34fcac359c54f68","files":{"application_py":{"hash":"c27b31d002b190b02d762716e7f57840","index":{"nums":[1,386,0,325,106,1,105],"html_filename":"application_py.html","relative_filename":"application.py"}},"generate_py":{"hash":"6472c4454035b9085ab4a70000a09404","index":{"nums":[1,1140,0,1070,682,0,682],"html_filename":"generate_py.html","relative_filename":"generate.py"}},"helpers_py":{"hash":"03e07f54fdcf922da47e0d5d1af5c4d8","index":{"nums":[1,9,0,3,2,0,2],"html_filename":"helpers_py.html","relative_filename":"helpers.py"}},"run_py":{"hash":"09b1440a943001e5c473ccc4a1ef1914","index":{"nums":[1,3,0,0,2,1,1],"html_filename":"run_py.html","relative_filename":"run.py"}}}}